{
   "describedBy": "https://raw.githubusercontent.com/AllenNeuralDynamics/aind-data-schema/main/src/aind_data_schema/data_description.py",
   "schema_version": "0.3.0",
   "license": "CC-BY-4.0",
   "creation_time": "16:30:01",
   "creation_date": "2022-02-21",
   "name": "ecephys_12345_2022-02-21_16-30-01",
   "institution": "AIND",
   "funding_source": [
      {
         "funder": "AIND",
         "grant_number": null,
         "fundee": null
      }
   ],
   "data_level": "raw data",
   "group": null,
   "project_name": null,
   "project_id": null,
   "restrictions": null,
   "modality": "ecephys",
   "subject_id": "12345"
}